DatetimeProcessing/main.py
DatetimeProcessing-0.2.1.dist-info/METADATA
DatetimeProcessing-0.2.1.dist-info/WHEEL
DatetimeProcessing-0.2.1.dist-info/top_level.txt
DatetimeProcessing-0.2.1.dist-info/RECORD
