Metadata-Version: 2.1
Name: DatetimeProcessing
Version: 0.2.1
Summary: Rules date_time
Author: ntt1210
Author-email: ndtan.fpt@gmail.com
